{"config": {"view": {"continuousWidth": 400, "continuousHeight": 300}}, "hconcat": [{"data": {"name": "data-26affd9c586dd4356bde9b3c990cbdf8"}, "mark": "bar", "encoding": {"color": {"field": "Age", "scale": {"domain": ["18 or Younger", "19 to 29", "30 to 60", "Over 60"], "range": ["#353795", "#c8b7d9", "#ef8872", "#dddddd"]}, "title": "Age", "type": "nominal"}, "tooltip": [{"field": "Age", "title": "Age", "type": "nominal"}, {"field": "Overall", "title": "Likelihood", "type": "quantitative"}], "x": {"field": "Age", "sort": ["18 or Younger", "19 to 29", "30 to 60", "Over 60"], "title": "", "type": "nominal"}, "y": {"field": "Overall", "title": "Overall Likelihood to Walk or Bike", "type": "quantitative"}}, "selection": {"selector019": {"type": "multi", "encodings": ["x"]}}, "title": "Click-select Category", "width": 100}, {"data": {"name": "data-ef2c9f3aade34b9b2ef9d21c5d071905"}, "mark": "line", "encoding": {"color": {"field": "Age", "type": "nominal"}, "x": {"field": "Distance", "type": "nominal"}, "y": {"field": "Likelihood", "type": "quantitative"}}, "transform": [{"filter": {"selection": "selector019"}}], "width": 300}], "$schema": "https://vega.github.io/schema/vega-lite/v4.17.0.json", "datasets": {"data-26affd9c586dd4356bde9b3c990cbdf8": [{"index": 0, "Age": "18 or Younger", "Overall": 0.6855947116798692}, {"index": 1, "Age": "19 to 29", "Overall": 0.3091075134910751}, {"index": 2, "Age": "30 to 60", "Overall": 0.23239836705542435}, {"index": 3, "Age": "Over 60", "Overall": 0.20385910685789366}], "data-ef2c9f3aade34b9b2ef9d21c5d071905": [{"Age": "18 or Younger", "Distance": "0.1 mile", "Likelihood": 0.9336204561394545}, {"Age": "19 to 29", "Distance": "0.1 mile", "Likelihood": 0.8025282975817623}, {"Age": "30 to 60", "Distance": "0.1 mile", "Likelihood": 0.760379994966635}, {"Age": "Over 60", "Distance": "0.1 mile", "Likelihood": 0.7577690276607565}, {"Age": "18 or Younger", "Distance": "0.2 mile", "Likelihood": 0.9243442849803404}, {"Age": "19 to 29", "Distance": "0.2 mile", "Likelihood": 0.7766938045797531}, {"Age": "30 to 60", "Distance": "0.2 mile", "Likelihood": 0.7266553063602511}, {"Age": "Over 60", "Distance": "0.2 mile", "Likelihood": 0.7154060537426896}, {"Age": "18 or Younger", "Distance": "0.3 mile", "Likelihood": 0.913891378862158}, {"Age": "19 to 29", "Distance": "0.3 mile", "Likelihood": 0.748538505195628}, {"Age": "30 to 60", "Distance": "0.3 mile", "Likelihood": 0.6901184872360666}, {"Age": "Over 60", "Distance": "0.3 mile", "Likelihood": 0.6688718052676901}, {"Age": "18 or Younger", "Distance": "0.4 mile", "Likelihood": 0.9021471435989967}, {"Age": "19 to 29", "Distance": "0.4 mile", "Likelihood": 0.7181216208065605}, {"Age": "30 to 60", "Distance": "0.4 mile", "Likelihood": 0.6510432236371326}, {"Age": "Over 60", "Distance": "0.4 mile", "Likelihood": 0.6187832113372775}, {"Age": "18 or Younger", "Distance": "0.5 mile", "Likelihood": 0.8889956859640152}, {"Age": "19 to 29", "Distance": "0.5 mile", "Likelihood": 0.6855709885531696}, {"Age": "30 to 60", "Distance": "0.5 mile", "Likelihood": 0.6098264209897672}, {"Age": "Over 60", "Distance": "0.5 mile", "Likelihood": 0.5660336973922475}, {"Age": "18 or Younger", "Distance": "0.6 mile", "Likelihood": 0.874322904728908}, {"Age": "19 to 29", "Distance": "0.6 mile", "Likelihood": 0.6510878012909064}, {"Age": "30 to 60", "Distance": "0.6 mile", "Likelihood": 0.5669793145838872}, {"Age": "Over 60", "Distance": "0.6 mile", "Likelihood": 0.5117445081772563}, {"Age": "18 or Younger", "Distance": "0.7 mile", "Likelihood": 0.8580203947519494}, {"Age": "19 to 29", "Distance": "0.7 mile", "Likelihood": 0.6149468981938525}, {"Age": "30 to 60", "Distance": "0.7 mile", "Likelihood": 0.5231065289867156}, {"Age": "Over 60", "Distance": "0.7 mile", "Likelihood": 0.4571768265538053}, {"Age": "18 or Younger", "Distance": "0.8 mile", "Likelihood": 0.8399901798765894}, {"Age": "19 to 29", "Distance": "0.8 mile", "Likelihood": 0.5774917400720916}, {"Age": "30 to 60", "Distance": "0.8 mile", "Likelihood": 0.47887425266465544}, {"Age": "Over 60", "Distance": "0.8 mile", "Likelihood": 0.40361778120989683}, {"Age": "18 or Younger", "Distance": "0.9 mile", "Likelihood": 0.8201502207825737}, {"Age": "19 to 29", "Distance": "0.9 mile", "Likelihood": 0.53912376231675}, {"Age": "30 to 60", "Distance": "0.9 mile", "Likelihood": 0.4349707646571284}, {"Age": "Over 60", "Distance": "0.9 mile", "Likelihood": 0.35226145300744377}, {"Age": "18 or Younger", "Distance": "1.0 mile", "Likelihood": 0.7984405506918894}, {"Age": "19 to 29", "Distance": "1.0 mile", "Likelihood": 0.5002865228950607}, {"Age": "30 to 60", "Distance": "1.0 mile", "Likelihood": 0.39206412968632215}, {"Age": "Over 60", "Distance": "1.0 mile", "Likelihood": 0.3041075874715181}, {"Age": "18 or Younger", "Distance": "1.1 miles", "Likelihood": 0.7748297782496271}, {"Age": "19 to 29", "Distance": "1.1 miles", "Likelihood": 0.46144582579312704}, {"Age": "30 to 60", "Distance": "1.1 miles", "Likelihood": 0.3507624860962021}, {"Age": "Over 60", "Distance": "1.1 miles", "Likelihood": 0.25989515219169534}, {"Age": "18 or Younger", "Distance": "1.2 miles", "Likelihood": 0.7493215719739574}, {"Age": "19 to 29", "Distance": "1.2 miles", "Likelihood": 0.42306764040383527}, {"Age": "30 to 60", "Distance": "1.2 miles", "Likelihood": 0.3115817938018825}, {"Age": "Over 60", "Distance": "1.2 miles", "Likelihood": 0.22007770175776895}, {"Age": "18 or Younger", "Distance": "1.3 miles", "Likelihood": 0.7219606201626287}, {"Age": "19 to 29", "Distance": "1.3 miles", "Likelihood": 0.3855960043282144}, {"Age": "30 to 60", "Distance": "1.3 miles", "Likelihood": 0.27492436467847486}, {"Age": "Over 60", "Distance": "1.3 miles", "Likelihood": 0.1848370097293826}, {"Age": "18 or Younger", "Distance": "1.4 miles", "Likelihood": 0.6928374662646374}, {"Age": "19 to 29", "Distance": "1.4 miles", "Likelihood": 0.34943309986170557}, {"Age": "30 to 60", "Distance": "1.4 miles", "Likelihood": 0.24106943692369404}, {"Age": "Over 60", "Distance": "1.4 miles", "Likelihood": 0.15412420607686367}, {"Age": "18 or Younger", "Distance": "1.5 miles", "Likelihood": 0.6620915787022713}, {"Age": "19 to 29", "Distance": "1.5 miles", "Likelihood": 0.3149233323644921}, {"Age": "30 to 60", "Distance": "1.5 miles", "Likelihood": 0.2101750470935331}, {"Age": "Over 60", "Distance": "1.5 miles", "Likelihood": 0.12771513522527128}, {"Age": "18 or Younger", "Distance": "1.6 miles", "Likelihood": 0.6299120512880266}, {"Age": "19 to 29", "Distance": "1.6 miles", "Likelihood": 0.2823426016373309}, {"Age": "30 to 60", "Distance": "1.6 miles", "Likelihood": 0.18228895642893705}, {"Age": "Over 60", "Distance": "1.6 miles", "Likelihood": 0.10526808763140316}, {"Age": "18 or Younger", "Distance": "1.7 miles", "Likelihood": 0.5965354631634957}, {"Age": "19 to 29", "Distance": "1.7 miles", "Likelihood": 0.2518931950538714}, {"Age": "30 to 60", "Distance": "1.7 miles", "Likelihood": 0.15736562165926468}, {"Age": "Over 60", "Distance": "1.7 miles", "Likelihood": 0.08637563514950898}, {"Age": "18 or Younger", "Distance": "1.8 miles", "Likelihood": 0.5622406576145808}, {"Age": "19 to 29", "Distance": "1.8 miles", "Likelihood": 0.2237040050752882}, {"Age": "30 to 60", "Distance": "1.8 miles", "Likelihood": 0.13528613860781888}, {"Age": "Over 60", "Distance": "1.8 miles", "Likelihood": 0.07060624359839816}, {"Age": "18 or Younger", "Distance": "1.9 miles", "Likelihood": 0.5273405082249024}, {"Age": "19 to 29", "Distance": "1.9 miles", "Likelihood": 0.1978352118352674}, {"Age": "30 to 60", "Distance": "1.9 miles", "Likelihood": 0.11587853769789988}, {"Age": "Over 60", "Distance": "1.9 miles", "Likelihood": 0.057534531141459865}, {"Age": "18 or Younger", "Distance": "2.0 miles", "Likelihood": 0.49217108785046143}, {"Age": "19 to 29", "Distance": "2.0 miles", "Likelihood": 0.1742862411256397}, {"Age": "30 to 60", "Distance": "2.0 miles", "Likelihood": 0.0989365247056168}, {"Age": "Over 60", "Distance": "2.0 miles", "Likelihood": 0.0467610942998471}, {"Age": "18 or Younger", "Distance": "2.1 miles", "Likelihood": 0.45707898403388225}, {"Age": "19 to 29", "Distance": "2.1 miles", "Likelihood": 0.15300571307216126}, {"Age": "30 to 60", "Distance": "2.1 miles", "Likelihood": 0.08423551837056198}, {"Age": "Over 60", "Distance": "2.1 miles", "Likelihood": 0.03792382564683401}, {"Age": "18 or Younger", "Distance": "2.2 miles", "Likelihood": 0.42240775291254284}, {"Age": "19 to 29", "Distance": "2.2 miles", "Likelihood": 0.13390219286494853}, {"Age": "30 to 60", "Distance": "2.2 miles", "Likelihood": 0.07154549271346285}, {"Age": "Over 60", "Distance": "2.2 miles", "Likelihood": 0.030702898094069675}, {"Age": "18 or Younger", "Distance": "2.3 miles", "Likelihood": 0.3884846228504322}, {"Age": "19 to 29", "Distance": "2.3 miles", "Likelihood": 0.11685477405279202}, {"Age": "30 to 60", "Distance": "2.3 miles", "Likelihood": 0.06064061814290439}, {"Age": "Over 60", "Distance": "2.3 miles", "Likelihood": 0.024821406743883598}, {"Age": "18 or Younger", "Distance": "2.4 miles", "Likelihood": 0.35560852424500367}, {"Age": "19 to 29", "Distance": "2.4 miles", "Likelihood": 0.10172279771255488}, {"Age": "30 to 60", "Distance": "2.4 miles", "Likelihood": 0.05130600357416694}, {"Age": "Over 60", "Distance": "2.4 miles", "Likelihood": 0.020043284937572636}, {"Age": "18 or Younger", "Distance": "2.5 miles", "Likelihood": 0.32404034049153185}, {"Age": "19 to 29", "Distance": "2.5 miles", "Likelihood": 0.08835428144824234}, {"Age": "30 to 60", "Distance": "2.5 miles", "Likelihood": 0.04334199876250126}, {"Age": "Over 60", "Distance": "2.5 miles", "Likelihood": 0.016169700508325096}, {"Age": "18 or Younger", "Distance": "2.6 miles", "Likelihood": 0.2939959840451947}, {"Age": "19 to 29", "Distance": "2.6 miles", "Likelihood": 0.07659286463395129}, {"Age": "30 to 60", "Distance": "2.6 miles", "Likelihood": 0.03656656242381991}, {"Age": "Over 60", "Distance": "2.6 miles", "Likelihood": 0.013034771136142041}, {"Age": "18 or Younger", "Distance": "2.7 miles", "Likelihood": 0.2656425573760717}, {"Age": "19 to 29", "Distance": "2.7 miles", "Likelihood": 0.06628325368709441}, {"Age": "30 to 60", "Distance": "2.7 miles", "Likelihood": 0.030816177595933157}, {"Age": "Over 60", "Distance": "2.7 miles", "Likelihood": 0.01050114436795021}, {"Age": "18 or Younger", "Distance": "2.8 miles", "Likelihood": 0.23909752218297534}, {"Age": "19 to 29", "Distance": "2.8 miles", "Likelihood": 0.05727527118445194}, {"Age": "30 to 60", "Distance": "2.8 miles", "Likelihood": 0.02594573375927641}, {"Age": "Over 60", "Distance": "2.8 miles", "Likelihood": 0.008455770737069131}, {"Age": "18 or Younger", "Distance": "2.9 miles", "Likelihood": 0.2144305223373091}, {"Age": "19 to 29", "Distance": "2.9 miles", "Likelihood": 0.04942668214232658}, {"Age": "30 to 60", "Distance": "2.9 miles", "Likelihood": 0.02182771872606941}, {"Age": "Over 60", "Distance": "2.9 miles", "Likelihood": 0.006806047095035094}, {"Age": "18 or Younger", "Distance": "3.0 miles", "Likelihood": 0.19166731803386966}, {"Age": "19 to 29", "Distance": "3.0 miles", "Likelihood": 0.0426050007905706}, {"Age": "30 to 60", "Distance": "3.0 miles", "Likelihood": 0.01835098683218888}, {"Age": "Over 60", "Distance": "3.0 miles", "Likelihood": 0.005476407399225976}]}}